chromiumspider/__init__.py
chromiumspider/core.py
chromiumspider-1.0.0.dist-info/LICENSE
chromiumspider-1.0.0.dist-info/METADATA
chromiumspider-1.0.0.dist-info/WHEEL
chromiumspider-1.0.0.dist-info/top_level.txt
chromiumspider-1.0.0.dist-info/RECORD
