Metadata-Version: 2.1
Name: chromiumspider
Version: 1.0.0
Summary: 一个自动管理ChromiumDriver版本的，基于Selenium开发的自动化测试爬虫框架。
Home-page: https://github.com/7emotions/ChromiumSpider
Author: Lorenzo Feng
Author-email: lorenzo.feng@njust.edu.cn
License: Apache License
Platform: all
Classifier: Intended Audience :: Developers
Classifier: Operating System :: OS Independent
Classifier: Natural Language :: Chinese (Simplified)
Classifier: Programming Language :: Python
Classifier: Programming Language :: Python :: 2
Classifier: Programming Language :: Python :: 2.7
Classifier: Programming Language :: Python :: 3
Classifier: Programming Language :: Python :: 3.5
Classifier: Programming Language :: Python :: 3.6
Classifier: Programming Language :: Python :: 3.7
Classifier: Programming Language :: Python :: 3.8
Classifier: Topic :: Software Development :: Libraries
License-File: LICENSE
Requires-Dist: selenium >=4.20.0
